<?xml version="1.0" encoding="utf-8"?>
<resources>
    <style name="TextInputStyleProfile" parent="Widget.MaterialComponents.TextInputLayout.OutlinedBox">
        <item name="boxCornerRadiusBottomStart">25dp</item>
        <item name="boxCornerRadiusBottomEnd">25dp</item>
        <item name="boxCornerRadiusTopStart">25dp</item>
        <item name="boxCornerRadiusTopEnd">25dp</item>
        <item name="android:layout_marginHorizontal">15dp</item>
        <item name="boxStrokeWidth">2dp</item>
        <item name="boxStrokeWidthFocused">2dp</item>
        <item name="errorIconDrawable">@null</item>
        <item name="hintEnabled">false</item>
    </style>
</resources>